{
  "display": {
    "icon": {
      "item": "peluche_bouboule_mod:peluche_bouboule_haut_de_forme"
    },
    "title": {
      "translate": "advancements.peluche_haut_de_forme.title"
    },
    "description": {
      "translate": "advancements.peluche_haut_de_forme.descr"
    },
    "frame": "task",
    "show_toast": true,
    "announce_to_chat": true,
    "hidden": false
  },
  "criteria": {
    "peluche_haut_de_forme": {
      "trigger": "minecraft:inventory_changed",
      "conditions": {
        "items": [
          {
            "items": [
              "peluche_bouboule_mod:peluche_bouboule_haut_de_forme"
            ],
            "count": {
              "min": 0,
              "max": 1
            }
          }
        ]
      }
    }
  },
  "parent": "peluche_bouboule_mod:demarrer_une_collection"
}